clinicadl/__init__.py
clinicadl/cmdline.py
clinicadl/generate/__init__.py
clinicadl/generate/generate.py
clinicadl/generate/generate_artifacts_cli.py
clinicadl/generate/generate_cli.py
clinicadl/generate/generate_hypometabolic_cli.py
clinicadl/generate/generate_random_cli.py
clinicadl/generate/generate_shepplogan_cli.py
clinicadl/generate/generate_trivial_cli.py
clinicadl/generate/generate_utils.py
clinicadl/hugging_face/hugging_face.py
clinicadl/hugging_face/hugging_face_cli.py
clinicadl/hugging_face/pull_cli.py
clinicadl/hugging_face/push_cli.py
clinicadl/interpret/__init__.py
clinicadl/interpret/gradients.py
clinicadl/interpret/interpret.py
clinicadl/interpret/interpret_cli.py
clinicadl/mlflow_test.py
clinicadl/predict/__init__.py
clinicadl/predict/predict.py
clinicadl/predict/predict_cli.py
clinicadl/prepare_data/__init__.py
clinicadl/prepare_data/prepare_data.py
clinicadl/prepare_data/prepare_data_cli.py
clinicadl/prepare_data/prepare_data_from_bids_cli.py
clinicadl/prepare_data/prepare_data_utils.py
clinicadl/quality_check/__init__.py
clinicadl/quality_check/pet_linear/__init__.py
clinicadl/quality_check/pet_linear/cli.py
clinicadl/quality_check/pet_linear/quality_check.py
clinicadl/quality_check/pet_linear/utils.py
clinicadl/quality_check/qc_cli.py
clinicadl/quality_check/t1_linear/__init__.py
clinicadl/quality_check/t1_linear/cli.py
clinicadl/quality_check/t1_linear/models.py
clinicadl/quality_check/t1_linear/quality_check.py
clinicadl/quality_check/t1_linear/utils.py
clinicadl/quality_check/t1_volume/__init__.py
clinicadl/quality_check/t1_volume/cli.py
clinicadl/quality_check/t1_volume/quality_check.py
clinicadl/quality_check/t1_volume/utils.py
clinicadl/random_search/__init__.py
clinicadl/random_search/random_search.py
clinicadl/random_search/random_search_cli.py
clinicadl/random_search/random_search_utils.py
clinicadl/resources/config/train_config.toml
clinicadl/resources/masks/README.md
clinicadl/resources/masks/__init__.py
clinicadl-1.6.1.dist-info/LICENSE.txt
clinicadl-1.6.1.dist-info/METADATA
clinicadl-1.6.1.dist-info/WHEEL
clinicadl-1.6.1.dist-info/entry_points.txt
clinicadl-1.6.1.dist-info/RECORD
