Metadata-Version: 2.1
Name: clinicadl
Version: 1.6.1
Summary: Framework for the reproducible processing of neuroimaging data with deep learning methods
Home-page: https://clinicadl.readthedocs.io
License: MIT
Keywords: bids,image processing,deep learning,neuroimaging,neuroscience
Author: ARAMIS Lab
Maintainer: Clinica developers
Maintainer-email: clinica-user@inria.fr
Requires-Python: >=3.8,<3.12
Classifier: Development Status :: 4 - Beta
Classifier: Environment :: Console
Classifier: Intended Audience :: Developers
Classifier: Intended Audience :: End Users/Desktop
Classifier: License :: OSI Approved :: MIT License
Classifier: Operating System :: OS Independent
Classifier: Programming Language :: Python :: 3
Classifier: Programming Language :: Python :: 3.8
Classifier: Programming Language :: Python :: 3.9
Classifier: Programming Language :: Python :: 3.10
Classifier: Programming Language :: Python :: 3.11
Classifier: Topic :: Scientific/Engineering :: Image Processing
Classifier: Topic :: Scientific/Engineering :: Medical Science Apps.
Requires-Dist: click (>=8,<9)
Requires-Dist: click-option-group (>=0.5,<0.6)
Requires-Dist: joblib (>=1.2.0,<2.0.0)
Requires-Dist: nilearn (>=0.9.2,<0.10.0)
Requires-Dist: numpy (>=1.17,<2.0)
Requires-Dist: pandas (>=1.2,<2.0)
Requires-Dist: pynvml
Requires-Dist: scikit-image (>=0.21,<0.22)
Requires-Dist: scikit-learn (>=1.0,<2.0)
Requires-Dist: tensorboard
Requires-Dist: toml
Requires-Dist: torch (>=2.1.0,<3.0.0)
Requires-Dist: torchio (>=0.18.90,<0.19.0)
Requires-Dist: torchvision
Requires-Dist: urllib3 (<2.0.0)
Project-URL: Documentation, https://clinicadl.readthedocs.io
Project-URL: Repository, https://github.com/aramis-lab/clinicadl.git
